htmailer/__init__.py
htmailer/htmailer.py
htmailer/resolver.py
htmailer-1.0.1.dist-info/License.md
htmailer-1.0.1.dist-info/METADATA
htmailer-1.0.1.dist-info/WHEEL
htmailer-1.0.1.dist-info/top_level.txt
htmailer-1.0.1.dist-info/RECORD
