Metadata-Version: 2.1
Name: htmailer
Version: 1.0.1
Summary: Htmessage is simple extension of django's official
Home-page: https://github.com/dino16m/htmailer
Author: Dino16m
Author-email: anselem16m@gmail.com
License: MIT
Platform: UNKNOWN
Classifier: License :: OSI Approved :: MIT License
Classifier: Programming Language :: Python :: 3
Classifier: Programming Language :: Python :: 3.7
Requires-Dist: django
